DescTC/__init__.py
DescTC-0.1.1.dist-info/LICENSE
DescTC-0.1.1.dist-info/METADATA
DescTC-0.1.1.dist-info/WHEEL
DescTC-0.1.1.dist-info/top_level.txt
DescTC-0.1.1.dist-info/RECORD
