Metadata-Version: 2.1
Name: DescTC
Version: 0.1.1
Summary: The package includes methods that condense large amounts of information about each variable of your dataset into easy-to-understand formats (table and charts) that clearly and effectively communicate important points.
Home-page: https://github.com/MarianeAlves/DescTC
Author: Mariane Alves
Author-email: mariane.estatistica@gmail.com
License: MIT
Keywords: describe,table,chart
Platform: UNKNOWN
Classifier: Programming Language :: Python :: 3
Classifier: License :: OSI Approved :: MIT License
Classifier: Operating System :: OS Independent
Requires-Python: >=3.6
Requires-Dist: pandas (>=1.1)
Requires-Dist: numpy (>=1.19)
Requires-Dist: matplotlib (>=3.3)
Requires-Dist: seaborn (>=0.11)
